competitionToolbox
