Metadata-Version: 1.0
Name: quantquestToolbox
Version: 2.2.0
Summary: The Toolbox for Quant Quest competition
Home-page: https://quant-quest.auquan.com
Author: Auquan
Author-email: info@auquan.com
License: MIT
Platform: UNKNOWN
